nicegui_ext/__init__.py
nicegui_ext/draggable.py
nicegui_ext/helpers.py
nicegui_ext/icons.py
nicegui_ext/md.py
nicegui_ext/native_file_picker.py
nicegui_ext/ui.py
nicegui_ext/auto/__init__.py
nicegui_ext/auto/auto_element.py
nicegui_ext/auto/class_element.py
nicegui_ext/auto/parser.py
nicegui_ext/auto/pydantic_element.py
nicegui_ext/auto/select.py
nicegui_extensions-0.0.4.dist-info/LICENSE
nicegui_extensions-0.0.4.dist-info/METADATA
nicegui_extensions-0.0.4.dist-info/WHEEL
nicegui_extensions-0.0.4.dist-info/top_level.txt
nicegui_extensions-0.0.4.dist-info/RECORD
