Metadata-Version: 2.1
Name: nicegui-extensions
Version: 0.0.4
Author-email: Žiga Ivanšek <ziga.ivansek@gmail.com>
License: MIT License
Project-URL: Repository, https://github.com/zigai/nicegui-extensions
Classifier: Intended Audience :: Developers
Classifier: License :: OSI Approved :: MIT License
Classifier: Operating System :: OS Independent
Classifier: Programming Language :: Python
Classifier: Programming Language :: Python :: 3.10
Classifier: Programming Language :: Python :: 3 :: Only
Classifier: Topic :: Software Development :: Libraries :: Python Modules
Requires-Python: >=3.10
License-File: LICENSE
Requires-Dist: stdl >=0.5.1
Requires-Dist: strto >=0.1.3
Requires-Dist: objinspect >=0.2.9
Requires-Dist: nicegui >=1.4.0
Provides-Extra: dev
Requires-Dist: black ; extra == 'dev'
Requires-Dist: pytest ; extra == 'dev'
Requires-Dist: ruff ; extra == 'dev'
Provides-Extra: pydantic
Requires-Dist: pydantic >=2.4.0 ; extra == 'pydantic'
Provides-Extra: test
Requires-Dist: pytest ; extra == 'test'
